goodbyecaptcha/__init__.py
goodbyecaptcha/audio.py
goodbyecaptcha/base.py
goodbyecaptcha/exceptions.py
goodbyecaptcha/goodbyecaptcha.example.yaml
goodbyecaptcha/image.py
goodbyecaptcha/predict.py
goodbyecaptcha/proxy.py
goodbyecaptcha/solver.py
goodbyecaptcha/speech.py
goodbyecaptcha/util.py
goodbyecaptcha/data/jquery.js
goodbyecaptcha/models/yolov3.cfg
goodbyecaptcha/models/yolov3.txt
goodbyecaptcha-2.4.2.dist-info/LICENSE.rst
goodbyecaptcha-2.4.2.dist-info/METADATA
goodbyecaptcha-2.4.2.dist-info/WHEEL
goodbyecaptcha-2.4.2.dist-info/top_level.txt
goodbyecaptcha-2.4.2.dist-info/RECORD
