Metadata-Version: 2.1
Name: goodbyecaptcha
Version: 2.4.2
Summary: An asynchronized Python library to automate solving ReCAPTCHA v2 by images/audio
Home-page: https://github.com/MacKey-255/GoodByeCatpcha
Author: MacKey-255 <mackeyfuturo@gmail.com>, Michael Mooney <mikeyy@mikeyy.com>
Author-email: mackeyfuturo@gmail.com, mikeyy@mikeyy.com
License: GPL-3.0
Keywords: captcha,recaptcha,Python3,google,cloudflare,mitm,solver captcha,automate solver,web scraping,bottinggoodbyecaptcha,solver recaptcha,image recognition
Platform: all
Classifier: Development Status :: 5 - Production/Stable
Classifier: Environment :: Console
Classifier: Environment :: Web Environment
Classifier: Environment :: Plugins
Classifier: Intended Audience :: Developers
Classifier: Intended Audience :: Education
Classifier: Intended Audience :: System Administrators
Classifier: Intended Audience :: Science/Research
Classifier: Intended Audience :: Information Technology
Classifier: License :: OSI Approved :: MIT License
Classifier: Natural Language :: English
Classifier: Operating System :: OS Independent
Classifier: Operating System :: Unix
Classifier: Programming Language :: Python :: 3.7
Classifier: Programming Language :: JavaScript
Classifier: Topic :: Scientific/Engineering
Classifier: Topic :: Scientific/Engineering :: Image Recognition
Classifier: Topic :: Scientific/Engineering :: Information Analysis
Classifier: Topic :: Software Development :: Libraries
Classifier: Topic :: Software Development :: Libraries :: Python Modules
Classifier: Topic :: Utilities
Requires-Dist: aiobotocore (==0.9.3)
Requires-Dist: aiofiles (==0.3.2)
Requires-Dist: aiohttp (==3.3.2)
Requires-Dist: appdirs (==1.4.3)
Requires-Dist: async-generator (==1.10)
Requires-Dist: async-timeout (==3.0.0)
Requires-Dist: attrs (==19.3.0)
Requires-Dist: beautifulsoup4 (==4.8.1)
Requires-Dist: botocore (==1.10.58)
Requires-Dist: certifi (==2019.9.11)
Requires-Dist: chardet (==3.0.4)
Requires-Dist: docutils (==0.15.2)
Requires-Dist: entrypoints (==0.3)
Requires-Dist: fake-useragent (==0.1.11)
Requires-Dist: flake8 (==3.5.0)
Requires-Dist: fuckcaptcha (==0.1.0)
Requires-Dist: idna (==2.8)
Requires-Dist: jmespath (==0.9.4)
Requires-Dist: mccabe (==0.6.1)
Requires-Dist: multidict (==4.6.1)
Requires-Dist: numpy (==1.17.4)
Requires-Dist: opencv-python (==4.1.2.30)
Requires-Dist: peewee (==3.11.2)
Requires-Dist: Pillow (==6.2.1)
Requires-Dist: pocketsphinx (==0.1.15)
Requires-Dist: psutil (==5.4.6)
Requires-Dist: pycodestyle (==2.3.1)
Requires-Dist: pydub (==0.22.1)
Requires-Dist: pyee (==7.0.1)
Requires-Dist: pyflakes (==1.6.0)
Requires-Dist: pyppeteer (==0.2.2)
Requires-Dist: pyppeteer-stealth (==1.0.0)
Requires-Dist: python-dateutil (==2.8.1)
Requires-Dist: PyYAML (==5.1.2)
Requires-Dist: requests (==2.22.0)
Requires-Dist: six (==1.13.0)
Requires-Dist: soupsieve (==1.9.5)
Requires-Dist: SpeechRecognition (==3.8.1)
Requires-Dist: tqdm (==4.46.0)
Requires-Dist: urllib3 (==1.25.9)
Requires-Dist: user-agent (==0.1.9)
Requires-Dist: websockets (==8.1)
Requires-Dist: wrapt (==1.11.2)
Requires-Dist: yarl (==1.3.0)
